<annotation>
	<folder>my-project-name</folder>
	<filename>cropped_272.jpg</filename>
	<path>/my-project-name/cropped_272.jpg</path>
	<source>
		<database>Unspecified</database>
	</source>
	<size>
		<width>640</width>
		<height>640</height>
		<depth>3</depth>
	</size>
	<object>
		<name>tile</name>
		<pose>Unspecified</pose>
		<truncated>0</truncated>
		<difficult>0</difficult>
		<bndbox>
			<xmin>179</xmin>
			<ymin>231</ymin>
			<xmax>255</xmax>
			<ymax>304</ymax>
		</bndbox>
	</object>
	<object>
		<name>tile</name>
		<pose>Unspecified</pose>
		<truncated>0</truncated>
		<difficult>0</difficult>
		<bndbox>
			<xmin>272</xmin>
			<ymin>217</ymin>
			<xmax>351</xmax>
			<ymax>288</ymax>
		</bndbox>
	</object>
	<object>
		<name>tile</name>
		<pose>Unspecified</pose>
		<truncated>0</truncated>
		<difficult>0</difficult>
		<bndbox>
			<xmin>367</xmin>
			<ymin>204</ymin>
			<xmax>444</xmax>
			<ymax>281</ymax>
		</bndbox>
	</object>
	<object>
		<name>tile</name>
		<pose>Unspecified</pose>
		<truncated>0</truncated>
		<difficult>0</difficult>
		<bndbox>
			<xmin>377</xmin>
			<ymin>296</ymin>
			<xmax>458</xmax>
			<ymax>372</ymax>
		</bndbox>
	</object>
	<object>
		<name>tile</name>
		<pose>Unspecified</pose>
		<truncated>0</truncated>
		<difficult>0</difficult>
		<bndbox>
			<xmin>286</xmin>
			<ymin>311</ymin>
			<xmax>363</xmax>
			<ymax>385</ymax>
		</bndbox>
	</object>
	<object>
		<name>tile</name>
		<pose>Unspecified</pose>
		<truncated>0</truncated>
		<difficult>0</difficult>
		<bndbox>
			<xmin>189</xmin>
			<ymin>328</ymin>
			<xmax>266</xmax>
			<ymax>398</ymax>
		</bndbox>
	</object>
	<object>
		<name>tile</name>
		<pose>Unspecified</pose>
		<truncated>0</truncated>
		<difficult>0</difficult>
		<bndbox>
			<xmin>207</xmin>
			<ymin>416</ymin>
			<xmax>284</xmax>
			<ymax>487</ymax>
		</bndbox>
	</object>
	<object>
		<name>tile</name>
		<pose>Unspecified</pose>
		<truncated>0</truncated>
		<difficult>0</difficult>
		<bndbox>
			<xmin>295</xmin>
			<ymin>408</ymin>
			<xmax>374</xmax>
			<ymax>474</ymax>
		</bndbox>
	</object>
	<object>
		<name>tile</name>
		<pose>Unspecified</pose>
		<truncated>0</truncated>
		<difficult>0</difficult>
		<bndbox>
			<xmin>387</xmin>
			<ymin>391</ymin>
			<xmax>469</xmax>
			<ymax>464</ymax>
		</bndbox>
	</object>
</annotation>